{
  "File Name": "143213_095.jpg",
  "Create Date": "2024-05-09 14:32:14+01:00",
  "Create Seconds Epoch": 1715261534.2,
  "Trigger": "External",
  "Subject Distance": 0.5425935974,
  "Exposure Time": "1/140",
  "ISO": 112,
  "Annotation": {
    "Source": "llava:13b",
    "Test": " The image shows a light fixture, specifically an artistic lamp that appears to be made of multiple interconnected pieces. These pieces could resemble petals or leaves, giving the lamp an organic and natural appearance. The design is abstract and modern, with the central hole allowing for light to pass through the structure."
  }
}
